CHANGES
INSTALL
LICENSE
MANIFEST.in
README.rst
setup.cfg
setup.py
redis3/__init__.py
redis3/_compat.py
redis3/client.py
redis3/connection.py
redis3/exceptions.py
redis3/lock.py
redis3/sentinel.py
redis3/utils.py
redis3.egg-info/PKG-INFO
redis3.egg-info/SOURCES.txt
redis3.egg-info/dependency_links.txt
redis3.egg-info/requires.txt
redis3.egg-info/top_level.txt
tests/__init__.py
tests/conftest.py
tests/test_commands.py
tests/test_connection.py
tests/test_connection_pool.py
tests/test_encoding.py
tests/test_lock.py
tests/test_monitor.py
tests/test_multiprocessing.py
tests/test_pipeline.py
tests/test_pubsub.py
tests/test_scripting.py
tests/test_sentinel.py